sanic_openid_connect_provider/__init__.py
sanic_openid_connect_provider/authorize_endpoint.py
sanic_openid_connect_provider/client.py
sanic_openid_connect_provider/exceptions.py
sanic_openid_connect_provider/handlers.py
sanic_openid_connect_provider/models/__init__.py
sanic_openid_connect_provider/models/aws_clients.py
sanic_openid_connect_provider/models/aws_code.py
sanic_openid_connect_provider/models/aws_token.py
sanic_openid_connect_provider/models/clients.py
sanic_openid_connect_provider/models/code.py
sanic_openid_connect_provider/models/redis_code.py
sanic_openid_connect_provider/models/redis_token.py
sanic_openid_connect_provider/models/token.py
sanic_openid_connect_provider/models/users.py
sanic_openid_connect_provider/provider.py
sanic_openid_connect_provider/templates/authorize.html
sanic_openid_connect_provider/templates/error.html
sanic_openid_connect_provider/templates/form-autosubmit.html
sanic_openid_connect_provider/templates/hidden_inputs.html
sanic_openid_connect_provider/token_endpoint.py
sanic_openid_connect_provider/utils.py
sanic_openid_connect_provider/validation.py
sanic_openid_connect_provider-0.9.0.dist-info/LICENSE
sanic_openid_connect_provider-0.9.0.dist-info/WHEEL
sanic_openid_connect_provider-0.9.0.dist-info/METADATA
sanic_openid_connect_provider-0.9.0.dist-info/RECORD
