Metadata-Version: 2.1
Name: sanic-openid-connect-provider
Version: 0.9.0
Summary: OpenID Provider framework for sanic
Home-page: https://github.com/terrycain/sanic-openid-provider
License: Apache-2.0
Keywords: sanic,openid,provider
Author: Terry Cain
Author-email: terry@terrys-home.co.uk
Requires-Python: >=3.6.2,<4.0
Classifier: Development Status :: 2 - Pre-Alpha
Classifier: Intended Audience :: Developers
Classifier: License :: OSI Approved :: Apache Software License
Classifier: License :: OSI Approved :: MIT License
Classifier: Natural Language :: English
Classifier: Programming Language :: Python :: 3
Classifier: Programming Language :: Python :: 3.6
Classifier: Programming Language :: Python :: 3.7
Classifier: Programming Language :: Python :: 3.8
Classifier: Programming Language :: Python :: 3.9
Provides-Extra: aws
Provides-Extra: redis
Requires-Dist: PyJWT (>=1.6.4)
Requires-Dist: aiohttp (>=3.4.4)
Requires-Dist: jwcrypto (>=0.6.0)
Requires-Dist: sanic (>=20.9.1)
Project-URL: Repository, https://github.com/terrycain/sanic-openid-provider
